<?xml version="1.0" encoding="UTF-8"?>
<TrustFrameworkPolicy PolicyId="B2C_1A_ProfileEdit" TenantId="udcsp-tenant.onmicrosoft.com" PublicPolicyUri="http://udcsp/B2C_1A_ProfileEdit" xmlns="http://schemas.microsoft.com/online/cpim/schemas/2013/06">
  <BasePolicy><TenantId>udcsp-tenant.onmicrosoft.com</TenantId><PolicyId>B2C_1A_TrustFrameworkExtensions</PolicyId></BasePolicy>
  <RelyingParty><DefaultUserJourney ReferenceId="ProfileEditWithEidasBridge" /><TechnicalProfile Id="PolicyProfile"><OutputClaims><OutputClaim ClaimTypeReferenceId="country" /><OutputClaim ClaimTypeReferenceId="eidasLoA" /><OutputClaim ClaimTypeReferenceId="nationalIdHash" /></OutputClaims></TechnicalProfile></RelyingParty>
  <!-- TODO: case-study scaffold — replace with real values when deploying -->
</TrustFrameworkPolicy>
